{
    "Aatrox": null,
    "Ahri": null,
    "Akali": null,
    "Akshan": null,
    "Alistar": null,
    "Ambessa": 50.0,
    "Amumu": 37.5,
    "Anivia": null,
    "Annie": null,
    "Aphelios": null,
    "Ashe": null,
    "Aurelion Sol": null,
    "Aurora": null,
    "Azir": null,
    "Bard": null,
    "Bel'Veth": 50.0,
    "Blitzcrank": null,
    "Brand": null,
    "Braum": null,
    "Briar": 50.0,
    "Caitlyn": null,
    "Camille": null,
    "Cassiopeia": null,
    "Cho'Gath": 33.33,
    "Corki": null,
    "Darius": null,
    "Diana": 65.0,
    "Dr. Mundo": 16.67,
    "Draven": null,
    "Ekko": 55.56,
    "Elise": 33.33,
    "Evelynn": 70.0,
    "Ezreal": null,
    "Fiddlesticks": 50.0,
    "Fiora": null,
    "Fizz": null,
    "Galio": null,
    "Gangplank": null,
    "Garen": null,
    "Gnar": null,
    "Gragas": 33.33,
    "Graves": 33.33,
    "Gwen": 60.0,
    "Hecarim": 47.06,
    "Heimerdinger": null,
    "Hwei": null,
    "Illaoi": null,
    "Irelia": null,
    "Ivern": 100.0,
    "Janna": null,
    "Jarvan IV": 55.17,
    "Jax": 57.14,
    "Jayce": null,
    "Jhin": null,
    "Jinx": null,
    "K'Sante": null,
    "Kai'Sa": null,
    "Kalista": null,
    "Karma": null,
    "Karthus": null,
    "Kassadin": null,
    "Katarina": null,
    "Kayle": null,
    "Kayn": 32.26,
    "Kennen": null,
    "Kha'Zix": 50.0,
    "Kindred": 50.0,
    "Kled": null,
    "Kog'Maw": null,
    "LeBlanc": null,
    "Lee Sin": 60.42,
    "Leona": null,
    "Lillia": 64.71,
    "Lissandra": null,
    "Lucian": null,
    "Lulu": null,
    "Lux": null,
    "Malphite": 100.0,
    "Malzahar": null,
    "Maokai": 25.0,
    "Master Yi": 40.0,
    "Mel": 100.0,
    "Milio": null,
    "Miss Fortune": null,
    "Mordekaiser": null,
    "Morgana": null,
    "Naafiri": 23.08,
    "Nami": null,
    "Nasus": 50.0,
    "Nautilus": null,
    "Neeko": 100.0,
    "Nidalee": 25.0,
    "Nilah": null,
    "No Champion": null,
    "Nocturne": 50.0,
    "Nunu & Willump": 45.45,
    "Olaf": 100.0,
    "Orianna": null,
    "Ornn": null,
    "Pantheon": 57.14,
    "Poppy": null,
    "Pyke": null,
    "Qiyana": 50.0,
    "Quinn": null,
    "Rakan": null,
    "Rammus": 44.44,
    "Rek'Sai": 33.33,
    "Rell": null,
    "Renata Glasc": null,
    "Renekton": 100.0,
    "Rengar": 40.0,
    "Riven": null,
    "Rumble": null,
    "Ryze": null,
    "Samira": null,
    "Sejuani": 66.67,
    "Senna": null,
    "Seraphine": null,
    "Shaco": 64.29,
    "Shen": 100.0,
    "Shyvana": 40.0,
    "Singed": null,
    "Sion": null,
    "Sivir": null,
    "Skarner": 50.0,
    "Smolder": null,
    "Sona": null,
    "Soraka": null,
    "Swain": null,
    "Sylas": 50.0,
    "Syndra": null,
    "Tahm Kench": null,
    "Taliyah": 50.0,
    "Talon": 66.67,
    "Taric": null,
    "Teemo": null,
    "Thresh": null,
    "Tristana": null,
    "Trundle": 31.25,
    "Tryndamere": null,
    "Twisted Fate": null,
    "Twitch": null,
    "Udyr": 25.0,
    "Urgot": 100.0,
    "Varus": null,
    "Vayne": null,
    "Veigar": null,
    "Vel'Koz": null,
    "Vex": null,
    "Vi": 69.23,
    "Viego": 54.55,
    "Viktor": null,
    "Vladimir": null,
    "Volibear": 43.75,
    "Warwick": 29.41,
    "Wukong": 38.46,
    "Xayah": null,
    "Xerath": null,
    "Xin Zhao": 66.67,
    "Yasuo": null,
    "Yone": null,
    "Yorick": null,
    "Yuumi": null,
    "Zac": 33.33,
    "Zed": 28.57,
    "Zeri": null,
    "Ziggs": null,
    "Zilean": null,
    "Zoe": null,
    "Zyra": 100.0
}