{
    "Aatrox": 100.0,
    "Ahri": null,
    "Akali": null,
    "Akshan": 100.0,
    "Alistar": null,
    "Ambessa": 47.22,
    "Amumu": 52.27,
    "Anivia": null,
    "Annie": null,
    "Aphelios": null,
    "Ashe": null,
    "Aurelion Sol": 50.0,
    "Aurora": null,
    "Azir": null,
    "Bard": 33.33,
    "Bel'Veth": 47.62,
    "Blitzcrank": 100.0,
    "Brand": 56.76,
    "Braum": null,
    "Briar": 51.57,
    "Caitlyn": null,
    "Camille": 60.0,
    "Cassiopeia": null,
    "Cho'Gath": 58.33,
    "Corki": 71.43,
    "Darius": 50.0,
    "Diana": 46.84,
    "Dr. Mundo": 52.13,
    "Draven": 50.0,
    "Ekko": 46.53,
    "Elise": 52.01,
    "Evelynn": 46.41,
    "Ezreal": 50.0,
    "Fiddlesticks": 49.43,
    "Fiora": null,
    "Fizz": null,
    "Galio": null,
    "Gangplank": null,
    "Garen": 85.71,
    "Gnar": null,
    "Gragas": 45.38,
    "Graves": 50.86,
    "Gwen": 49.03,
    "Hecarim": 52.49,
    "Heimerdinger": 50.0,
    "Hwei": null,
    "Illaoi": null,
    "Irelia": null,
    "Ivern": 46.48,
    "Janna": null,
    "Jarvan IV": 48.55,
    "Jax": 49.01,
    "Jayce": 50.0,
    "Jhin": 66.67,
    "Jinx": 100.0,
    "K'Sante": null,
    "Kai'Sa": 50.0,
    "Kalista": null,
    "Karma": null,
    "Kassadin": null,
    "Katarina": null,
    "Kayle": 100.0,
    "Kayn": 47.68,
    "Kennen": null,
    "Kha'Zix": 51.08,
    "Kindred": 50.91,
    "Kled": null,
    "Kog'Maw": null,
    "LeBlanc": null,
    "Lee Sin": 50.99,
    "Leona": 100.0,
    "Lillia": 50.13,
    "Lissandra": null,
    "Lucian": null,
    "Lulu": null,
    "Lux": null,
    "Malphite": 66.67,
    "Malzahar": null,
    "Maokai": 51.72,
    "Master Yi": 44.93,
    "Mel": null,
    "Milio": null,
    "Miss Fortune": null,
    "Mordekaiser": 48.39,
    "Morgana": 64.0,
    "Naafiri": 50.0,
    "Nami": null,
    "Nasus": 47.46,
    "Nautilus": 100.0,
    "Neeko": 53.85,
    "Nidalee": 47.22,
    "Nilah": 50.0,
    "No Champion": null,
    "Nocturne": 48.03,
    "Nunu & Willump": 49.51,
    "Olaf": 51.11,
    "Orianna": null,
    "Ornn": null,
    "Pantheon": 54.75,
    "Poppy": 44.64,
    "Pyke": 100.0,
    "Qiyana": 56.38,
    "Quinn": null,
    "Rakan": null,
    "Rammus": 49.44,
    "Rek'Sai": 50.41,
    "Rell": 50.0,
    "Renata Glasc": null,
    "Renekton": null,
    "Rengar": 51.71,
    "Riven": 25.0,
    "Rumble": 51.72,
    "Ryze": null,
    "Samira": null,
    "Sejuani": 49.26,
    "Senna": null,
    "Seraphine": null,
    "Sett": 100.0,
    "Shaco": 49.79,
    "Shen": 47.06,
    "Shyvana": 47.86,
    "Singed": null,
    "Sion": 25.0,
    "Sivir": null,
    "Skarner": 49.25,
    "Smolder": null,
    "Sona": 100.0,
    "Soraka": 100.0,
    "Swain": 100.0,
    "Sylas": 59.32,
    "Syndra": null,
    "Tahm Kench": null,
    "Taliyah": 43.4,
    "Talon": 49.82,
    "Taric": 50.0,
    "Teemo": 54.72,
    "Thresh": 100.0,
    "Tristana": null,
    "Trundle": 48.67,
    "Tryndamere": 33.33,
    "Twisted Fate": 100.0,
    "Twitch": 59.09,
    "Udyr": 44.18,
    "Urgot": 50.0,
    "Varus": null,
    "Vayne": 75.0,
    "Veigar": null,
    "Vel'Koz": null,
    "Vex": null,
    "Vi": 54.1,
    "Viego": 51.1,
    "Viktor": null,
    "Vladimir": null,
    "Volibear": 48.37,
    "Warwick": 52.81,
    "Wukong": 52.86,
    "Xayah": 100.0,
    "Xerath": null,
    "Xin Zhao": 48.09,
    "Yasuo": null,
    "Yone": 100.0,
    "Yorick": 61.11,
    "Yuumi": 100.0,
    "Zac": 52.3,
    "Zed": 54.61,
    "Zeri": 100.0,
    "Ziggs": null,
    "Zilean": null,
    "Zoe": null,
    "Zyra": 53.33
}