{
    "Aatrox": 100.0,
    "Ahri": 33.33,
    "Akali": 62.5,
    "Akshan": 50.0,
    "Alistar": null,
    "Ambessa": null,
    "Amumu": null,
    "Anivia": 66.67,
    "Annie": null,
    "Aphelios": null,
    "Ashe": null,
    "Aurelion Sol": null,
    "Aurora": 60.0,
    "Azir": 33.33,
    "Bard": null,
    "Bel'Veth": null,
    "Blitzcrank": null,
    "Brand": null,
    "Braum": null,
    "Briar": null,
    "Caitlyn": null,
    "Camille": null,
    "Cassiopeia": null,
    "Cho'Gath": null,
    "Corki": 20.0,
    "Darius": null,
    "Diana": 75.0,
    "Dr. Mundo": 100.0,
    "Draven": null,
    "Ekko": 20.0,
    "Elise": null,
    "Evelynn": null,
    "Ezreal": null,
    "Fiddlesticks": null,
    "Fiora": null,
    "Fizz": 100.0,
    "Galio": 80.0,
    "Gangplank": 100.0,
    "Garen": null,
    "Gnar": null,
    "Gragas": null,
    "Graves": null,
    "Gwen": null,
    "Hecarim": null,
    "Heimerdinger": null,
    "Hwei": 37.5,
    "Illaoi": null,
    "Irelia": 50.0,
    "Ivern": null,
    "Janna": null,
    "Jarvan IV": null,
    "Jax": 66.67,
    "Jayce": null,
    "Jhin": null,
    "Jinx": null,
    "K'Sante": null,
    "Kai'Sa": 50.0,
    "Kalista": null,
    "Karma": null,
    "Karthus": null,
    "Kassadin": null,
    "Katarina": 54.55,
    "Kayle": 33.33,
    "Kayn": null,
    "Kennen": null,
    "Kha'Zix": null,
    "Kled": null,
    "Kog'Maw": null,
    "LeBlanc": 50.0,
    "Lee Sin": null,
    "Leona": null,
    "Lillia": null,
    "Lissandra": null,
    "Lucian": 100.0,
    "Lulu": null,
    "Lux": 25.0,
    "Malphite": null,
    "Malzahar": 80.0,
    "Maokai": null,
    "Master Yi": null,
    "Mel": 57.14,
    "Milio": null,
    "Miss Fortune": null,
    "Mordekaiser": null,
    "Morgana": 100.0,
    "Naafiri": null,
    "Nami": null,
    "Nasus": 100.0,
    "Nautilus": null,
    "Neeko": 100.0,
    "Nidalee": null,
    "Nilah": null,
    "No Champion": null,
    "Nocturne": null,
    "Nunu & Willump": null,
    "Olaf": 100.0,
    "Orianna": 33.33,
    "Ornn": null,
    "Pantheon": 50.0,
    "Poppy": null,
    "Pyke": null,
    "Qiyana": 33.33,
    "Quinn": 100.0,
    "Rakan": null,
    "Rammus": null,
    "Rek'Sai": null,
    "Rell": null,
    "Renata Glasc": null,
    "Renekton": null,
    "Rengar": null,
    "Riven": 100.0,
    "Rumble": null,
    "Ryze": 100.0,
    "Samira": null,
    "Sejuani": null,
    "Senna": null,
    "Seraphine": null,
    "Sett": null,
    "Shaco": null,
    "Shen": null,
    "Shyvana": null,
    "Singed": null,
    "Sion": null,
    "Sivir": null,
    "Skarner": null,
    "Smolder": null,
    "Sona": null,
    "Soraka": null,
    "Swain": 100.0,
    "Sylas": 54.55,
    "Syndra": 100.0,
    "Tahm Kench": null,
    "Taliyah": 66.67,
    "Talon": 75.0,
    "Taric": null,
    "Teemo": null,
    "Thresh": null,
    "Tristana": 100.0,
    "Trundle": null,
    "Tryndamere": null,
    "Twisted Fate": 35.71,
    "Twitch": null,
    "Udyr": null,
    "Urgot": null,
    "Varus": null,
    "Vayne": null,
    "Veigar": 40.0,
    "Vel'Koz": null,
    "Vex": 66.67,
    "Vi": null,
    "Viego": null,
    "Viktor": 30.0,
    "Vladimir": 50.0,
    "Volibear": null,
    "Warwick": null,
    "Wukong": null,
    "Xayah": null,
    "Xerath": 80.0,
    "Xin Zhao": null,
    "Yasuo": 60.0,
    "Yone": 83.33,
    "Yorick": null,
    "Yuumi": null,
    "Zac": null,
    "Zed": 45.45,
    "Zeri": null,
    "Ziggs": null,
    "Zilean": 50.0,
    "Zoe": null,
    "Zyra": null
}