{
    "Aatrox": 57.58,
    "Ahri": 50.59,
    "Akali": 47.76,
    "Akshan": 48.29,
    "Alistar": 20.0,
    "Ambessa": 53.93,
    "Amumu": 50.0,
    "Anivia": 44.0,
    "Annie": 46.45,
    "Aphelios": 72.73,
    "Ashe": 44.44,
    "Aurelion Sol": 45.73,
    "Aurora": 51.87,
    "Azir": 49.04,
    "Bard": 75.0,
    "Bel'Veth": 66.67,
    "Blitzcrank": 100.0,
    "Brand": 51.67,
    "Braum": null,
    "Briar": 36.67,
    "Caitlyn": 62.0,
    "Camille": 50.0,
    "Cassiopeia": 48.55,
    "Cho'Gath": 46.97,
    "Corki": 53.56,
    "Darius": 60.0,
    "Diana": 46.74,
    "Dr. Mundo": 40.82,
    "Draven": 56.52,
    "Ekko": 43.67,
    "Elise": 50.0,
    "Evelynn": 50.0,
    "Ezreal": 55.56,
    "Fiddlesticks": 31.82,
    "Fiora": 33.33,
    "Fizz": 42.72,
    "Galio": 47.94,
    "Gangplank": 55.1,
    "Garen": 63.33,
    "Gnar": 66.67,
    "Gragas": 50.0,
    "Graves": 37.5,
    "Gwen": 45.0,
    "Hecarim": 100.0,
    "Heimerdinger": 49.47,
    "Hwei": 49.28,
    "Illaoi": 37.5,
    "Irelia": 46.25,
    "Ivern": 57.14,
    "Janna": null,
    "Jarvan IV": 60.0,
    "Jax": 68.75,
    "Jayce": 50.64,
    "Jhin": 46.43,
    "Jinx": 57.14,
    "K'Sante": 45.83,
    "Kai'Sa": 54.24,
    "Kalista": 50.0,
    "Karma": 50.63,
    "Karthus": 51.02,
    "Kassadin": 47.13,
    "Katarina": 48.05,
    "Kayle": 43.37,
    "Kayn": null,
    "Kennen": 39.09,
    "Kha'Zix": 66.67,
    "Kindred": 25.0,
    "Kled": 44.12,
    "Kog'Maw": 40.54,
    "LeBlanc": 49.83,
    "Lee Sin": 65.52,
    "Leona": 100.0,
    "Lillia": 50.0,
    "Lissandra": 48.73,
    "Lucian": 63.83,
    "Lulu": 42.42,
    "Lux": 49.8,
    "Malphite": 54.24,
    "Malzahar": 47.82,
    "Maokai": 100.0,
    "Master Yi": 68.75,
    "Milio": 50.0,
    "Miss Fortune": 62.5,
    "Mordekaiser": 50.0,
    "Morgana": 43.54,
    "Naafiri": 51.01,
    "Nami": 100.0,
    "Nasus": 46.0,
    "Nautilus": 70.0,
    "Neeko": 48.8,
    "Nidalee": 50.75,
    "Nilah": 85.71,
    "No Champion": null,
    "Nocturne": 35.29,
    "Nunu & Willump": 47.56,
    "Olaf": 25.0,
    "Orianna": 48.71,
    "Ornn": 50.0,
    "Pantheon": 47.34,
    "Poppy": 42.86,
    "Pyke": 60.61,
    "Qiyana": 46.29,
    "Quinn": 43.71,
    "Rakan": 42.31,
    "Rammus": 33.33,
    "Rek'Sai": 40.0,
    "Rell": 100.0,
    "Renata Glasc": null,
    "Renekton": 57.45,
    "Rengar": 100.0,
    "Riven": 43.59,
    "Rumble": 42.5,
    "Ryze": 54.67,
    "Samira": 42.11,
    "Sejuani": 50.0,
    "Senna": 58.33,
    "Seraphine": 47.42,
    "Sett": 44.0,
    "Shaco": 44.44,
    "Shen": 42.42,
    "Shyvana": 80.0,
    "Singed": 53.33,
    "Sion": 50.0,
    "Sivir": 62.96,
    "Skarner": null,
    "Smolder": 59.6,
    "Sona": 50.0,
    "Soraka": 57.89,
    "Swain": 50.16,
    "Sylas": 49.71,
    "Syndra": 48.29,
    "Tahm Kench": 63.64,
    "Taliyah": 46.68,
    "Talon": 45.63,
    "Taric": 100.0,
    "Teemo": 58.97,
    "Thresh": 100.0,
    "Tristana": 47.06,
    "Trundle": 50.0,
    "Tryndamere": 39.71,
    "Twisted Fate": 49.92,
    "Twitch": 41.18,
    "Udyr": 40.0,
    "Urgot": 66.67,
    "Varus": 55.0,
    "Vayne": 57.5,
    "Veigar": 47.06,
    "Vel'Koz": 49.16,
    "Vex": 50.57,
    "Vi": 33.33,
    "Viego": 57.5,
    "Viktor": 44.51,
    "Vladimir": 46.12,
    "Volibear": 44.44,
    "Warwick": 33.33,
    "Wukong": 55.56,
    "Xayah": null,
    "Xerath": 45.2,
    "Xin Zhao": 60.0,
    "Yasuo": 46.93,
    "Yone": 52.39,
    "Yorick": 48.48,
    "Yuumi": 85.71,
    "Zac": 46.51,
    "Zed": 46.39,
    "Zeri": 48.48,
    "Ziggs": 51.56,
    "Zilean": 52.38,
    "Zoe": 47.75,
    "Zyra": 50.0
}