{
    "Aatrox": 53.85,
    "Ahri": 64.86,
    "Akali": 100.0,
    "Akshan": 69.23,
    "Alistar": 50.19,
    "Ambessa": 100.0,
    "Amumu": 51.4,
    "Anivia": 63.64,
    "Annie": 54.1,
    "Aphelios": 100.0,
    "Ashe": 54.64,
    "Aurelion Sol": 53.33,
    "Aurora": 41.18,
    "Azir": 60.0,
    "Bard": 50.16,
    "Bel'Veth": 100.0,
    "Blitzcrank": 54.36,
    "Brand": 56.42,
    "Braum": 49.7,
    "Briar": 50.0,
    "Caitlyn": 74.19,
    "Camille": 53.13,
    "Cassiopeia": 40.0,
    "Cho'Gath": 57.14,
    "Corki": 50.0,
    "Darius": 78.57,
    "Diana": 33.33,
    "Dr. Mundo": 29.41,
    "Draven": 85.71,
    "Ekko": 50.0,
    "Elise": 52.73,
    "Evelynn": 44.44,
    "Ezreal": 68.18,
    "Fiddlesticks": 55.05,
    "Fiora": 62.5,
    "Fizz": 54.55,
    "Galio": 45.62,
    "Gangplank": 100.0,
    "Garen": 66.67,
    "Gnar": 50.0,
    "Gragas": 51.15,
    "Graves": null,
    "Gwen": 100.0,
    "Hecarim": null,
    "Heimerdinger": 44.55,
    "Hwei": 52.43,
    "Illaoi": 60.0,
    "Irelia": 100.0,
    "Ivern": 42.03,
    "Janna": 50.28,
    "Jarvan IV": 49.56,
    "Jax": 50.0,
    "Jayce": 50.0,
    "Jhin": 76.0,
    "Jinx": 75.0,
    "K'Sante": 63.16,
    "Kai'Sa": 88.89,
    "Kalista": 40.0,
    "Karma": 51.27,
    "Karthus": 57.14,
    "Kassadin": 100.0,
    "Katarina": 81.82,
    "Kayle": 50.0,
    "Kayn": 66.67,
    "Kennen": 40.74,
    "Kha'Zix": 66.67,
    "Kindred": 50.0,
    "Kled": 46.67,
    "Kog'Maw": 62.86,
    "LeBlanc": 53.27,
    "Lee Sin": 58.06,
    "Lillia": 100.0,
    "Lissandra": 65.31,
    "Lucian": 50.0,
    "Lulu": 51.36,
    "Lux": 50.76,
    "Malphite": 59.18,
    "Malzahar": 41.18,
    "Maokai": 52.19,
    "Master Yi": 77.27,
    "Mel": 59.26,
    "Milio": 50.03,
    "Miss Fortune": 63.33,
    "Mordekaiser": 45.16,
    "Morgana": 50.12,
    "Naafiri": 60.0,
    "Nami": 50.38,
    "Nasus": 58.33,
    "Nautilus": 55.12,
    "Neeko": 54.31,
    "Nidalee": 53.11,
    "Nilah": null,
    "No Champion": null,
    "Nocturne": 80.0,
    "Nunu & Willump": 48.39,
    "Olaf": 100.0,
    "Orianna": 62.96,
    "Ornn": 65.12,
    "Pantheon": 52.35,
    "Poppy": 50.59,
    "Pyke": 52.3,
    "Qiyana": 55.56,
    "Quinn": 52.17,
    "Rakan": 50.23,
    "Rammus": 52.17,
    "Rek'Sai": 50.0,
    "Rell": 49.4,
    "Renata Glasc": null,
    "Renekton": 60.0,
    "Rengar": 50.0,
    "Riven": 33.33,
    "Rumble": 85.71,
    "Ryze": 100.0,
    "Samira": 50.0,
    "Sejuani": 38.1,
    "Senna": 52.94,
    "Seraphine": 51.17,
    "Sett": 63.73,
    "Shaco": 48.39,
    "Shen": 53.9,
    "Shyvana": null,
    "Singed": 58.06,
    "Sion": 59.42,
    "Sivir": 50.0,
    "Skarner": 61.11,
    "Smolder": 62.5,
    "Sona": 50.22,
    "Soraka": 48.59,
    "Swain": 50.75,
    "Sylas": 59.59,
    "Syndra": 55.26,
    "Tahm Kench": 47.89,
    "Taliyah": 53.45,
    "Talon": 75.0,
    "Taric": 46.72,
    "Teemo": 50.26,
    "Thresh": 50.25,
    "Tristana": 50.0,
    "Trundle": 55.07,
    "Tryndamere": 50.0,
    "Twisted Fate": 50.55,
    "Twitch": 61.49,
    "Udyr": 80.0,
    "Urgot": 60.0,
    "Varus": 48.39,
    "Vayne": 60.0,
    "Veigar": 57.6,
    "Vel'Koz": 50.71,
    "Vex": 51.52,
    "Vi": 61.54,
    "Viego": 40.0,
    "Viktor": 70.0,
    "Vladimir": 75.0,
    "Volibear": 80.0,
    "Warwick": 57.14,
    "Wukong": 63.16,
    "Xayah": 100.0,
    "Xerath": 54.59,
    "Xin Zhao": 71.43,
    "Yasuo": 61.54,
    "Yone": 77.78,
    "Yorick": null,
    "Yuumi": 53.82,
    "Zac": 54.22,
    "Zed": 56.52,
    "Zeri": 100.0,
    "Ziggs": 60.0,
    "Zilean": 49.41,
    "Zoe": 49.84,
    "Zyra": 52.56
}