{
    "Aatrox": null,
    "Ahri": null,
    "Akali": null,
    "Akshan": null,
    "Alistar": 38.24,
    "Ambessa": 100.0,
    "Amumu": null,
    "Anivia": null,
    "Annie": 50.0,
    "Aphelios": null,
    "Ashe": null,
    "Aurelion Sol": 100.0,
    "Aurora": null,
    "Azir": null,
    "Bard": 46.15,
    "Bel'Veth": null,
    "Blitzcrank": 58.82,
    "Brand": 50.0,
    "Braum": 45.83,
    "Briar": null,
    "Caitlyn": null,
    "Camille": 33.33,
    "Cassiopeia": null,
    "Cho'Gath": null,
    "Corki": null,
    "Darius": null,
    "Diana": null,
    "Dr. Mundo": null,
    "Draven": null,
    "Ekko": null,
    "Elise": 40.0,
    "Evelynn": null,
    "Ezreal": null,
    "Fiddlesticks": 66.67,
    "Fiora": null,
    "Fizz": null,
    "Galio": 100.0,
    "Gangplank": null,
    "Garen": null,
    "Gnar": null,
    "Gragas": null,
    "Graves": null,
    "Gwen": null,
    "Hecarim": null,
    "Heimerdinger": 50.0,
    "Hwei": 50.0,
    "Illaoi": null,
    "Irelia": null,
    "Ivern": 100.0,
    "Janna": 23.53,
    "Jarvan IV": null,
    "Jax": null,
    "Jayce": null,
    "Jhin": null,
    "Jinx": null,
    "K'Sante": null,
    "Kai'Sa": null,
    "Kalista": null,
    "Karma": 36.84,
    "Karthus": 100.0,
    "Kassadin": null,
    "Katarina": null,
    "Kayle": null,
    "Kayn": null,
    "Kennen": null,
    "Kha'Zix": null,
    "Kindred": null,
    "Kled": 100.0,
    "Kog'Maw": null,
    "LeBlanc": 33.33,
    "Lee Sin": 66.67,
    "Leona": 45.83,
    "Lillia": null,
    "Lissandra": null,
    "Lucian": null,
    "Lulu": 56.76,
    "Lux": 50.0,
    "Malphite": 25.0,
    "Malzahar": null,
    "Maokai": 14.29,
    "Master Yi": null,
    "Mel": 44.44,
    "Milio": 39.29,
    "Miss Fortune": null,
    "Mordekaiser": null,
    "Morgana": 27.27,
    "Naafiri": null,
    "Nami": 38.3,
    "Nasus": null,
    "Nautilus": 41.94,
    "Neeko": 25.0,
    "Nidalee": 50.0,
    "Nilah": null,
    "No Champion": null,
    "Nocturne": null,
    "Nunu & Willump": null,
    "Olaf": null,
    "Orianna": null,
    "Ornn": null,
    "Pantheon": 31.25,
    "Poppy": 41.67,
    "Pyke": 53.13,
    "Quinn": null,
    "Rakan": 57.14,
    "Rammus": 100.0,
    "Rek'Sai": null,
    "Rell": 52.38,
    "Renata Glasc": null,
    "Renekton": null,
    "Rengar": null,
    "Riven": null,
    "Rumble": 100.0,
    "Ryze": null,
    "Samira": null,
    "Sejuani": null,
    "Senna": 52.94,
    "Seraphine": 75.0,
    "Sett": null,
    "Shaco": 60.0,
    "Shen": 25.0,
    "Shyvana": null,
    "Singed": null,
    "Sion": null,
    "Sivir": null,
    "Skarner": null,
    "Smolder": null,
    "Sona": 36.36,
    "Soraka": 40.0,
    "Swain": 37.5,
    "Sylas": 57.14,
    "Syndra": null,
    "Tahm Kench": 73.33,
    "Taliyah": 100.0,
    "Talon": null,
    "Taric": 25.0,
    "Teemo": 50.0,
    "Thresh": 42.86,
    "Tristana": null,
    "Trundle": null,
    "Tryndamere": 100.0,
    "Twisted Fate": null,
    "Twitch": 50.0,
    "Udyr": null,
    "Urgot": null,
    "Varus": null,
    "Vayne": null,
    "Veigar": 50.0,
    "Vel'Koz": 50.0,
    "Vex": 100.0,
    "Vi": null,
    "Viego": null,
    "Viktor": 100.0,
    "Vladimir": null,
    "Volibear": null,
    "Warwick": null,
    "Wukong": 100.0,
    "Xayah": null,
    "Xerath": 36.84,
    "Xin Zhao": 100.0,
    "Yasuo": 100.0,
    "Yone": null,
    "Yorick": null,
    "Yuumi": 34.38,
    "Zac": null,
    "Zed": null,
    "Zeri": null,
    "Ziggs": 100.0,
    "Zilean": 36.36,
    "Zoe": 40.0,
    "Zyra": 75.0
}