{
    "Aatrox": 49.9,
    "Ahri": 57.14,
    "Akali": 54.55,
    "Akshan": 48.31,
    "Alistar": 42.86,
    "Ambessa": 51.88,
    "Amumu": 100.0,
    "Anivia": 50.0,
    "Annie": 47.83,
    "Aphelios": 66.67,
    "Ashe": 47.83,
    "Aurelion Sol": 45.83,
    "Aurora": 48.43,
    "Azir": 44.12,
    "Bard": 60.0,
    "Bel'Veth": 76.47,
    "Blitzcrank": null,
    "Brand": 57.14,
    "Braum": 100.0,
    "Briar": 48.78,
    "Caitlyn": 69.7,
    "Camille": 52.54,
    "Cassiopeia": 52.38,
    "Cho'Gath": 49.02,
    "Corki": 51.43,
    "Darius": 53.59,
    "Diana": 62.5,
    "Dr. Mundo": 48.81,
    "Draven": 39.29,
    "Ekko": 61.76,
    "Elise": 57.69,
    "Evelynn": 100.0,
    "Ezreal": 33.33,
    "Fiddlesticks": 52.17,
    "Fiora": 51.06,
    "Fizz": 58.33,
    "Galio": 55.56,
    "Garen": 51.7,
    "Gnar": 54.42,
    "Gragas": 50.2,
    "Graves": 46.67,
    "Gwen": 51.73,
    "Hecarim": 100.0,
    "Heimerdinger": 52.89,
    "Hwei": 62.5,
    "Illaoi": 57.01,
    "Irelia": 49.92,
    "Ivern": 42.5,
    "Janna": 75.0,
    "Jarvan IV": 64.52,
    "Jax": 53.36,
    "Jayce": 53.29,
    "Jhin": 63.16,
    "Jinx": 66.67,
    "K'Sante": 51.52,
    "Kai'Sa": 60.53,
    "Kalista": 42.11,
    "Karma": 44.44,
    "Karthus": 65.22,
    "Kassadin": 28.57,
    "Katarina": 66.67,
    "Kayle": 47.05,
    "Kayn": 57.99,
    "Kennen": 53.76,
    "Kha'Zix": 40.0,
    "Kindred": 80.0,
    "Kled": 48.77,
    "Kog'Maw": 45.45,
    "LeBlanc": 59.09,
    "Lee Sin": 51.4,
    "Leona": 100.0,
    "Lillia": 66.67,
    "Lissandra": 52.94,
    "Lucian": 66.23,
    "Lulu": 47.42,
    "Lux": 60.0,
    "Malphite": 46.7,
    "Malzahar": 51.69,
    "Maokai": 63.64,
    "Master Yi": 50.0,
    "Mel": 34.62,
    "Milio": 100.0,
    "Miss Fortune": 80.0,
    "Mordekaiser": 49.07,
    "Morgana": 55.56,
    "Naafiri": 52.73,
    "Nami": 100.0,
    "Nasus": 50.78,
    "Nautilus": 53.13,
    "Neeko": 53.33,
    "Nidalee": 51.47,
    "Nilah": 57.14,
    "No Champion": null,
    "Nocturne": 47.55,
    "Nunu & Willump": 33.33,
    "Olaf": 48.57,
    "Orianna": 50.0,
    "Ornn": 50.05,
    "Pantheon": 55.48,
    "Poppy": 47.81,
    "Pyke": 100.0,
    "Qiyana": 54.84,
    "Quinn": 48.81,
    "Rakan": null,
    "Rammus": 50.0,
    "Rek'Sai": 54.05,
    "Rell": null,
    "Renata Glasc": null,
    "Renekton": 54.78,
    "Rengar": 51.65,
    "Riven": 50.29,
    "Rumble": 52.02,
    "Ryze": 49.7,
    "Samira": 16.67,
    "Sejuani": 53.52,
    "Senna": 48.15,
    "Seraphine": 100.0,
    "Sett": 49.78,
    "Shaco": 66.22,
    "Shen": 47.56,
    "Shyvana": 62.96,
    "Singed": 52.53,
    "Sion": 49.21,
    "Sivir": 50.0,
    "Skarner": 42.86,
    "Smolder": 66.14,
    "Sona": 75.0,
    "Soraka": 40.0,
    "Swain": 49.15,
    "Sylas": 47.04,
    "Syndra": 38.46,
    "Tahm Kench": 51.4,
    "Taliyah": 33.33,
    "Talon": 66.67,
    "Taric": 50.0,
    "Teemo": 50.47,
    "Thresh": 100.0,
    "Tristana": 59.09,
    "Trundle": 52.24,
    "Tryndamere": 50.53,
    "Twisted Fate": 56.34,
    "Twitch": 71.43,
    "Udyr": 50.0,
    "Urgot": 47.44,
    "Varus": 52.26,
    "Vayne": 52.32,
    "Veigar": 52.08,
    "Vel'Koz": 36.36,
    "Vex": 14.29,
    "Vi": 60.0,
    "Viego": 52.94,
    "Viktor": 51.28,
    "Vladimir": 48.92,
    "Volibear": 53.3,
    "Warwick": 48.2,
    "Wukong": 53.13,
    "Xayah": 100.0,
    "Xerath": 42.86,
    "Xin Zhao": 53.43,
    "Yasuo": 51.92,
    "Yone": 56.56,
    "Yorick": 51.19,
    "Yuumi": 66.67,
    "Zac": 48.86,
    "Zed": 52.38,
    "Zeri": 76.47,
    "Ziggs": 37.5,
    "Zilean": 44.44,
    "Zoe": 64.71,
    "Zyra": 57.14
}